{
  "US:AAPL": 165.845,
  "US:ABBV": 164.995,
  "US:AFL": 66.08,
  "US:AMGN": 245.596,
  "US:AOS": 69.29,
  "US:ATO": 115.999,
  "US:AVGO": 633.55,
  "RO:BIO": 0.674,
  "US:BLK": 669.434,
  "US:BMY": 70.74,
  "RO:BNET": 0.299,
  "US:CBOE": 140.22,
  "US:CLX": 165.08,
  "US:CMI": 235.0425,
  "US:CPB": 53.8,
  "US:CSCO": 47.215,
  "US:CVX": 169.43,
  "US:ED": 99.895,
  "US:ELV": 464.4,
  "US:EVLV": 3.095,
  "US:GD": 223.29,
  "US:HD": 301.49,
  "US:HII": 208.19,
  "US:HRL": 39.84,
  "US:HYLN": 1.3,
  "US:ICE": 107.04,
  "US:INTC": 29.34,
  "US:JNJ": 164.65,
  "US:JPM": 139.57,
  "US:KMB": 145.67,
  "US:KO": 63.675,
  "US:KR": 48.06,
  "US:LMT": 479.66,
  "US:LYB": 92.72,
  "RO:M": 18.1,
  "RO:MAM": 2.95,
  "US:MMM": 106.6324,
  "US:MO": 46.75,
  "US:MRK": 116.435,
  "US:MSFT": 280.215,
  "US:NEE": 77.79,
  "US:NKE": 126.24,
  "RO:NRF": 5.98,
  "US:NSP": 121.945,
  "US:O": 62.035,
  "US:PEP": 189.04,
  "US:PFE": 39.63,
  "US:PG": 156.9,
  "US:PM": 98.52,
  "US:PNW": 80.835,
  "US:PRU": 84.55,
  "RO:R2512AE": 92.8,
  "RO:R2603AE": 91,
  "US:RGA": 140.51,
  "US:SBUX": 109.9,
  "US:SJI": 36.09,
  "US:SJM": 152.53,
  "US:SNA": 257.98,
  "RO:SNG": 39.4,
  "US:STOR": 32.21,
  "US:T": 17.725,
  "RO:TLV": 19.5,
  "US:TROW": 111.03,
  "RO:TRP": 0.62,
  "US:TRV": 179.69,
  "US:TXN": 174.33,
  "US:UGI": 34.03,
  "US:UL": 54.545,
  "US:UNM": 40.9399,
  "RO:VIV25E": 4.48,
  "US:VZ": 36.9381,
  "US:WBA": 35.44,
  "US:WBD": 13.21,
  "RO:WINE": 10.1,
  "US:WM": 166.01,
  "RO:R2804AE": 102.37
}