{
  "US:AAPL": 160.25,
  "US:ABBV": 158.05,
  "US:AFL": 62.87,
  "US:AMGN": 238.03,
  "US:AOS": 66.73,
  "US:ATO": 109.375,
  "US:AVGO": 636.17,
  "RO:BIO": 0.644,
  "US:BLK": 645.06,
  "US:BMY": 67.68,
  "RO:BNET": 0.2995,
  "US:CBOE": 129.38,
  "US:CLX": 157.5,
  "US:CMI": 223.97,
  "US:CPB": 54.54,
  "US:CSCO": 50.51,
  "US:CVX": 156.18,
  "US:ED": 95.05,
  "US:ELV": 456.85,
  "US:EVLV": 2.82,
  "US:GD": 223.45,
  "US:HD": 283.09,
  "US:HII": 199.95,
  "US:HRL": 38.66,
  "US:HYLN": 2.135,
  "US:ICE": 97.51,
  "US:INTC": 29.36,
  "US:JNJ": 152.65,
  "US:JPM": 124.93,
  "US:KMB": 130.495,
  "US:KO": 60.9,
  "US:KR": 49.05,
  "US:LMT": 474.67,
  "US:LYB": 86.59,
  "RO:M": 17,
  "RO:MAM": 3.03,
  "US:MMM": 101.16,
  "US:MO": 43.965,
  "US:MRK": 104.83,
  "US:MSFT": 280.57,
  "US:NEE": 75.69,
  "US:NKE": 120.71,
  "RO:NRF": 5.86,
  "US:NSP": 115.61,
  "US:O": 61.07,
  "US:PEP": 179.09,
  "US:PFE": 40.3975,
  "US:PG": 146.745,
  "US:PM": 90.77,
  "US:PNW": 77.22,
  "US:PRU": 77.61,
  "RO:R2512AE": 91.0999,
  "RO:R2603AE": 89.6,
  "US:RGA": 127.56,
  "US:SBUX": 98.34,
  "US:SJI": 36.09,
  "US:SJM": 154.71,
  "US:SNA": 234.4,
  "RO:SNG": 38.3,
  "US:STOR": 32.21,
  "US:T": 18.62,
  "RO:TLV": 19.66,
  "US:TROW": 109.65,
  "RO:TRP": 0.54,
  "US:TRV": 164.95,
  "US:TXN": 179.51,
  "US:UGI": 33.155,
  "US:UL": 51.4,
  "US:UNM": 38.01,
  "RO:VIV25E": 5.93,
  "US:VZ": 37.675,
  "US:WBA": 32.7,
  "US:WBD": 14,
  "RO:WINE": 9.12,
  "US:WM": 154.49
}