{
  "US:AAPL": 158.395,
  "US:ABBV": 158.19,
  "US:AFL": 63.67,
  "US:AMGN": 236.32,
  "US:AOS": 67.57,
  "US:ATO": 110.485,
  "US:AVGO": 633.58,
  "RO:BIO": 0.644,
  "US:BLK": 649.67,
  "US:BMY": 68.54,
  "RO:BNET": 0.3,
  "US:CBOE": 130.89,
  "US:CLX": 158.22,
  "US:CMI": 226.09,
  "US:CPB": 54.8,
  "US:CSCO": 50.695,
  "US:CVX": 157.85,
  "US:ED": 95.19,
  "US:ELV": 465.23,
  "US:EVLV": 2.765,
  "US:GD": 225.2,
  "US:HD": 283.185,
  "US:HII": 203.12,
  "US:HRL": 39.02,
  "US:HYLN": 2.12,
  "US:ICE": 98.22,
  "US:INTC": 29.4693,
  "US:JNJ": 153.7073,
  "US:JPM": 128.98,
  "US:KMB": 130.02,
  "US:KO": 61.315,
  "US:KR": 49,
  "US:LMT": 474.26,
  "US:LYB": 88.7,
  "RO:M": 17.38,
  "RO:MAM": 3.03,
  "US:MMM": 101.67,
  "US:MO": 44.305,
  "US:MRK": 107.27,
  "US:MSFT": 276.56,
  "US:NEE": 75.805,
  "US:NKE": 118.49,
  "RO:NRF": 5.87,
  "US:NSP": 116.8,
  "US:O": 61.2747,
  "US:PEP": 179.74,
  "US:PFE": 40.31,
  "US:PG": 146.34,
  "US:PM": 92.65,
  "US:PNW": 77.81,
  "US:PRU": 79.52,
  "RO:R2512AE": 91.3999,
  "RO:R2603AE": 88.79,
  "US:RGA": 130.4,
  "US:SBUX": 98.88,
  "US:SJI": 36.09,
  "US:SJM": 156.58,
  "US:SNA": 237.18,
  "RO:SNG": 38.3,
  "US:STOR": 32.21,
  "US:T": 18.87,
  "RO:TLV": 19.64,
  "US:TROW": 108.985,
  "RO:TRP": 0.547,
  "US:TRV": 166.985,
  "US:TXN": 177.51,
  "US:UGI": 33.56,
  "US:UL": 51.795,
  "US:UNM": 39.1,
  "RO:VIV25E": 5.93,
  "US:VZ": 38.007,
  "US:WBA": 33.2048,
  "US:WBD": 14.36,
  "RO:WINE": 9.09,
  "US:WM": 154.845
}