{
  "US:AAPL": 155.373,
  "US:ABBV": 149.73,
  "US:AFL": 69.39,
  "US:AMGN": 236.391,
  "US:AOS": 67.9894,
  "US:ATO": 115.005,
  "US:AVGO": 607.15,
  "RO:BIO": 0.664,
  "US:BLK": 717.34,
  "US:BMY": 70.51,
  "RO:BNET": 0.298,
  "US:CBOE": 127.705,
  "US:CLX": 152.68,
  "US:CMI": 253.585,
  "US:CPB": 50.66,
  "US:CSCO": 50.97,
  "US:CVX": 167.945,
  "US:ED": 90.275,
  "US:ELV": 488.43,
  "US:EVLV": 2.915,
  "US:GD": 231.29,
  "US:HD": 320.1275,
  "US:HII": 220.09,
  "US:HRL": 44.795,
  "US:HYLN": 3.3538,
  "US:ICE": 107.52,
  "US:INTC": 28.685,
  "US:JNJ": 158.42,
  "US:JPM": 143.025,
  "US:KMB": 126.195,
  "US:KO": 59.245,
  "US:KR": 43.75,
  "US:LMT": 473.345,
  "US:LYB": 98.57,
  "RO:M": 19.84,
  "RO:MAM": 3.3,
  "US:MMM": 112.0125,
  "US:MO": 47.225,
  "US:MRK": 107.01,
  "US:MSFT": 266.02,
  "US:NEE": 76.17,
  "US:NKE": 126.92,
  "RO:NRF": 6.99,
  "US:NSP": 121.465,
  "US:O": 66.42,
  "US:PEP": 175.525,
  "US:PFE": 42.885,
  "US:PG": 137.705,
  "US:PM": 99.94,
  "US:PNW": 74.26,
  "US:PRU": 103.64,
  "RO:R2512AE": 93.5,
  "RO:R2603AE": 93,
  "US:RGA": 149.94,
  "US:SBUX": 108.96,
  "US:SJI": 36.09,
  "US:SJM": 146.75,
  "US:SNA": 252.42,
  "RO:SNG": 40.65,
  "US:STOR": 32.21,
  "US:T": 19.0456,
  "RO:TLV": 19.9,
  "US:TROW": 120,
  "RO:TRP": 0.589,
  "US:TRV": 183.78,
  "US:TXN": 177.82,
  "US:UGI": 39.04,
  "US:UL": 50.865,
  "US:UNM": 42.95,
  "RO:VIV25E": 23.8,
  "US:VZ": 39.925,
  "US:WBA": 36.375,
  "US:WBD": 15.4436,
  "RO:WINE": 8.9,
  "US:WM": 152.285
}